aas_core3/__init__.py
aas_core3/common.py
aas_core3/common.pyi
aas_core3/constants.py
aas_core3/constants.pyi
aas_core3/enum.py
aas_core3/jsonization.py
aas_core3/jsonization.pyi
aas_core3/stringification.py
aas_core3/stringification.pyi
aas_core3/types.py
aas_core3/types.pyi
aas_core3.0_micropython-1.0.3.dist-info/LICENSE
aas_core3.0_micropython-1.0.3.dist-info/METADATA
aas_core3.0_micropython-1.0.3.dist-info/WHEEL
aas_core3.0_micropython-1.0.3.dist-info/top_level.txt
aas_core3.0_micropython-1.0.3.dist-info/RECORD
