Metadata-Version: 2.1
Name: aas-core3.0-micropython
Version: 1.0.3
Summary: Manipulate and de/serialize Asset Administration Shells in Micropython.
Home-page: https://github.com/aas-core-works/aas-core3.0-micropython
Author: Marko Ristin
Author-email: marko@ristin.ch
License: License :: OSI Approved :: MIT License
Keywords: asset administration shell sdk industry 4.0 industrie i4.0 industry iot iiot
Classifier: Programming Language :: Python :: Implementation :: MicroPython
Classifier: Development Status :: 5 - Production/Stable
Classifier: License :: OSI Approved :: MIT License
License-File: LICENSE
